pypeeve/__init__.py
pypeeve/version.py
pypeeve/logger/__init__.py
pypeeve/logger/_logger.py
pypeeve-1.0.1.dist-info/LICENSE
pypeeve-1.0.1.dist-info/METADATA
pypeeve-1.0.1.dist-info/WHEEL
pypeeve-1.0.1.dist-info/top_level.txt
pypeeve-1.0.1.dist-info/RECORD
