Metadata-Version: 2.1
Name: pypeeve
Version: 1.0.1
Summary: A Python Library For All Python Pet Peeves
Author-email: Kallol Das <kalloldash@gmail.com>
Keywords: python,library
Classifier: Programming Language :: Python :: 3
Classifier: Programming Language :: Python :: 3.7
Classifier: Programming Language :: Python :: 3.8
Classifier: Programming Language :: Python :: 3.9
Classifier: Programming Language :: Python :: 3.10
Requires-Python: >=3.7
License-File: LICENSE
